cfn_policy_validator/__init__.py
cfn_policy_validator/application_error.py
cfn_policy_validator/argument_actions.py
cfn_policy_validator/canonical_user_id.py
cfn_policy_validator/client.py
cfn_policy_validator/cloud_trail_attributes.py
cfn_policy_validator/logger.py
cfn_policy_validator/main.py
cfn_policy_validator/parameters.py
cfn_policy_validator/rest_api_attributes.py
cfn_policy_validator/version.py
cfn_policy_validator/cfn_tools/__init__.py
cfn_policy_validator/cfn_tools/cfn_loader.py
cfn_policy_validator/cfn_tools/cfn_object.py
cfn_policy_validator/cfn_tools/common_schema.py
cfn_policy_validator/cfn_tools/regex_patterns.py
cfn_policy_validator/cfn_tools/schema_validator.py
cfn_policy_validator/cfn_tools/yaml_loader.py
cfn_policy_validator/parsers/__init__.py
cfn_policy_validator/parsers/account_config.py
cfn_policy_validator/parsers/identity.py
cfn_policy_validator/parsers/identity_schemas.py
cfn_policy_validator/parsers/output.py
cfn_policy_validator/parsers/resource/__init__.py
cfn_policy_validator/parsers/resource/api_gateway.py
cfn_policy_validator/parsers/resource/backup.py
cfn_policy_validator/parsers/resource/cloud_trail.py
cfn_policy_validator/parsers/resource/code_artifact.py
cfn_policy_validator/parsers/resource/kms.py
cfn_policy_validator/parsers/resource/lambda_aws.py
cfn_policy_validator/parsers/resource/parser.py
cfn_policy_validator/parsers/resource/s3.py
cfn_policy_validator/parsers/resource/s3_express.py
cfn_policy_validator/parsers/resource/secrets_manager.py
cfn_policy_validator/parsers/resource/sns.py
cfn_policy_validator/parsers/resource/sqs.py
cfn_policy_validator/parsers/utils/__init__.py
cfn_policy_validator/parsers/utils/arn_generator.py
cfn_policy_validator/parsers/utils/arn_generator_schemas.py
cfn_policy_validator/parsers/utils/cfn_to_arn_map.json
cfn_policy_validator/parsers/utils/conditions_evaluator.py
cfn_policy_validator/parsers/utils/cycle_detection.py
cfn_policy_validator/parsers/utils/node_evaluator.py
cfn_policy_validator-0.0.36.dist-info/licenses/LICENSE
cfn_policy_validator-0.0.36.dist-info/METADATA
cfn_policy_validator-0.0.36.dist-info/WHEEL
cfn_policy_validator-0.0.36.dist-info/entry_points.txt
cfn_policy_validator-0.0.36.dist-info/top_level.txt
cfn_policy_validator-0.0.36.dist-info/RECORD
