Metadata-Version: 2.4
Name: cfn-policy-validator
Version: 0.0.36
Summary: Parses IAM identity-based and resource-based policies from a CloudFormation template and runs them through IAM Access Analyzer checks.
Home-page: https://github.com/awslabs/aws-cloudformation-iam-policy-validator
Author: matluttr
Author-email: matluttr@amazon.com
License: MIT-0
Keywords: cfn-policy-validator aws iam access-analyzer cloudformation
Classifier: Intended Audience :: Developers
Classifier: License :: OSI Approved :: MIT License
Classifier: Natural Language :: English
Classifier: Programming Language :: Python :: 3.8
Classifier: Programming Language :: Python :: 3.9
Classifier: Programming Language :: Python :: 3.10
Classifier: Programming Language :: Python :: 3.11
Classifier: Programming Language :: Python :: 3.12
Requires-Python: >=3.8
License-File: LICENSE
Requires-Dist: boto3>=1.34.124
Requires-Dist: pyYAML>=5.3
Requires-Dist: urllib3>=1.25
Requires-Dist: jsonschema>=4.21
Dynamic: author
Dynamic: author-email
Dynamic: classifier
Dynamic: description
Dynamic: description-content-type
Dynamic: home-page
Dynamic: keywords
Dynamic: license
Dynamic: license-file
Dynamic: requires-dist
Dynamic: requires-python
Dynamic: summary
